LICENSE
wrapenvars/__init__.py
wrapenvars-0.1.0.dist-info/LICENSE
wrapenvars-0.1.0.dist-info/WHEEL
wrapenvars-0.1.0.dist-info/METADATA
wrapenvars-0.1.0.dist-info/RECORD
